Henson-2.2.0.dist-info/DESCRIPTION.rst
Henson-2.2.0.dist-info/METADATA
Henson-2.2.0.dist-info/RECORD
Henson-2.2.0.dist-info/WHEEL
Henson-2.2.0.dist-info/entry_points.txt
Henson-2.2.0.dist-info/metadata.json
Henson-2.2.0.dist-info/top_level.txt
henson/__init__.py
henson/__main__.py
henson/base.py
henson/cli.py
henson/config.py
henson/exceptions.py
henson/extensions.py
henson/contrib/__init__.py
henson/contrib/retry/__init__.py
henson/contrib/sphinx/__init__.py
