Metadata-Version: 2.0
Name: Henson
Version: 2.2.0
Summary: A framework for running a Python service driven by a consumer
Home-page: https://henson.readthedocs.io
Author: Aditya Ghosh, Leonard Bedner, Zack Morris, and others
Author-email: henson@iheart.com
License: Apache License, Version 2.0
Platform: UNKNOWN
Classifier: Development Status :: 4 - Beta
Classifier: Intended Audience :: Developers
Classifier: License :: OSI Approved :: Apache Software License
Classifier: Natural Language :: English
Classifier: Operating System :: POSIX
Classifier: Programming Language :: Python
Classifier: Programming Language :: Python :: 3.8
Classifier: Programming Language :: Python :: 3.9
Classifier: Programming Language :: Python :: 3 :: Only
Classifier: Topic :: Software Development :: Libraries :: Application Frameworks
Provides-Extra: sphinx
Requires-Dist: argh
Requires-Dist: watchdog (>=0.8.3)
Provides-Extra: sphinx
Requires-Dist: sphinx (<1.7.1); extra == 'sphinx'
Requires-Dist: sphinxcontrib-autoprogram (>=0.1.3); extra == 'sphinx'
